Evmlab-0.3.0.0.1.dist-info/METADATA
Evmlab-0.3.0.0.1.dist-info/RECORD
Evmlab-0.3.0.0.1.dist-info/WHEEL
Evmlab-0.3.0.0.1.dist-info/top_level.txt
evmlab/__init__.py
evmlab/__main__.py
evmlab/compiler.py
evmlab/context.py
evmlab/contract.py
evmlab/etherchain.py
evmlab/evmtrace.py
evmlab/genesis.py
evmlab/multiapi.py
evmlab/opcodes.py
evmlab/reproduce.py
evmlab/source_map.py
evmlab/utils.py
evmlab/vm.py
evmlab/tools/__init__.py
evmlab/tools/opviewer.py
evmlab/tools/reproducer/__init__.py
evmlab/tools/reproducer/reproducer.py
evmlab/tools/reproducer/templates/index.html
