Metadata-Version: 2.1
Name: Evmlab
Version: 0.3.0.0.1
Summary: Ethereum EVM utilities
Home-page: https://github.com/ethereum/evmlab/
Author: Martin Holst Swende
Author-email: martin.swende@ethereum.org
License: GPLv3
Download-URL: https://github.com/ethereum/evmlab/tarball/v0.3.0.0.1
Keywords: ethereum,transaction,debugger
Platform: UNKNOWN
Provides-Extra: consolegui
Provides-Extra: abidecoder
Provides-Extra: docker
Requires-Dist: requests
Requires-Dist: web3
Requires-Dist: eth-hash[pycryptodome]
Requires-Dist: rlp (>=1.0)
Provides-Extra: abidecoder
Requires-Dist: ethereum-input-decoder; extra == 'abidecoder'
Provides-Extra: consolegui
Requires-Dist: urwid; extra == 'consolegui'
Provides-Extra: docker
Requires-Dist: docker (==3.0.0); extra == 'docker'
